{
  "project_info": {
    "project_number": "229542484733",
    "firebase_url": "https://carebot-872bb-default-rtdb.firebaseio.com",
    "project_id": "carebot-872bb",
    "storage_bucket": "carebot-872bb.firebasestorage.app"
  },
  "client": [
    {
      "client_info": {
        "mobilesdk_app_id": "1:229542484733:android:54ba951191a99e36f7fc94",
        "android_client_info": {
          "package_name": "com.healthguys.carebot"
        }
      },
      "oauth_client": [
        {
          "client_id": "229542484733-7i5v1o41m57mt121qadp7pdgq03sake9.apps.googleusercontent.com",
          "client_type": 1,
          "android_info": {
            "package_name": "com.healthguys.carebot",
            "certificate_hash": "154e521707415e2ede107e4d1a7869e939f269c4"
          }
        },
        {
          "client_id": "229542484733-p52lls6f8fkb4qhd7e6v346jb7583psq.apps.googleusercontent.com",
          "client_type": 1,
          "android_info": {
            "package_name": "com.healthguys.carebot",
            "certificate_hash": "5e8f16062ea3cd2c4a0d547876baa6f38cabf625"
          }
        },
        {
          "client_id": "229542484733-p01olacr9ia3qvn589dgpb7no1cs2kmb.apps.googleusercontent.com",
          "client_type": 3
        }
      ],
      "api_key": [
        {
          "current_key": "AIzaSyBBQz8199JiavwXtDGKA1HMLQrjnSBC3kI"
        }
      ],
      "services": {
        "appinvite_service": {
          "other_platform_oauth_client": [
            {
              "client_id": "229542484733-p01olacr9ia3qvn589dgpb7no1cs2kmb.apps.googleusercontent.com",
              "client_type": 3
            },
            {
              "client_id": "229542484733-9ut1d66l8rqcn3adeiotlhp3hpd8u12s.apps.googleusercontent.com",
              "client_type": 2,
              "ios_info": {
                "bundle_id": "com.healthguys.carebot"
              }
            }
          ]
        }
      }
    }
  ],
  "configuration_version": "1"
}